ae_module/__init__.py
ae_module/ae_aws_s3.py
ae_module/ae_collect_state.py
ae_module/ae_db.py
ae_module/ae_env_manager.py
ae_module/ae_file_util.py
ae_module/ae_get_data.py
ae_module/ae_logger.py
ae_module/ae_manage_cache_data.py
ae_module/ae_neo4j.py
ae_module/ae_telegram_constant.py
ae_module/ae_telegram_message.py
ae_module/ae_util.py
ae_module/ae_worker.py
ae_module-0.1.5.dist-info/METADATA
ae_module-0.1.5.dist-info/WHEEL
ae_module-0.1.5.dist-info/top_level.txt
ae_module-0.1.5.dist-info/RECORD
