Metadata-Version: 2.1
Name: ae-module
Version: 0.1.5
Summary: ae_module for Africa Elephant Project
Home-page: https://github.com/AfricaElephant/ae_module.git
Author: harry
Author-email: africaelephant@gmail.com
License: UNKNOWN
Download-URL: https://github.com/AfricaElephant/ae_module.git/archive/0.0.tar.gz
Keywords: ae_module
Platform: UNKNOWN
Classifier: Programming Language :: Python :: 3
Classifier: Programming Language :: Python :: 3.2
Classifier: Programming Language :: Python :: 3.3
Classifier: Programming Language :: Python :: 3.4
Classifier: Programming Language :: Python :: 3.5
Classifier: Programming Language :: Python :: 3.6
Classifier: Programming Language :: Python :: 3.7
Classifier: Programming Language :: Python :: 3.8
Requires-Python: >=3
